stargazerz/__init__.py
stargazerz/stargazer_crawler.py
stargazerz-0.0.2.dist-info/LICENSE
stargazerz-0.0.2.dist-info/METADATA
stargazerz-0.0.2.dist-info/WHEEL
stargazerz-0.0.2.dist-info/top_level.txt
stargazerz-0.0.2.dist-info/RECORD
