Metadata-Version: 2.1
Name: stargazerz
Version: 0.0.2
Summary: Instantly Retrieve Email Addresses and Usernames of Stargazers from Designated Repositories, Achieving Unparalleled Speed and Efficiency - All Without the Need for an API Key
Home-page: https://github.com/Frikallo/stargazerz
Author: Noah Kay
Author-email: noahkay13@gmail.com
Classifier: Development Status :: 3 - Alpha
Classifier: Intended Audience :: Developers
Classifier: License :: OSI Approved :: Apache Software License
Classifier: Operating System :: OS Independent
Classifier: Programming Language :: Python
Classifier: Programming Language :: Python :: 3
Classifier: Programming Language :: Python :: 3.6
Classifier: Programming Language :: Python :: 3.7
Classifier: Programming Language :: Python :: 3.8
Classifier: Programming Language :: Python :: 3.9
Classifier: Programming Language :: Python :: 3.10
License-File: LICENSE
Requires-Dist: beautifulsoup4 ==4.12.2
Requires-Dist: bs4 ==0.0.1
Requires-Dist: requests ==2.31.0
Requires-Dist: tqdm ==4.66.1
